pipseq/__init__.py
pipseq/_modidx.py
pipseq/path.py
pipseq/pttn.py
pipseq-0.0.2.dist-info/LICENSE
pipseq-0.0.2.dist-info/METADATA
pipseq-0.0.2.dist-info/WHEEL
pipseq-0.0.2.dist-info/entry_points.txt
pipseq-0.0.2.dist-info/top_level.txt
pipseq-0.0.2.dist-info/RECORD
