Metadata-Version: 2.1
Name: pipseq
Version: 0.0.2
Summary: In Vitro Fertilization
Home-page: https://github.com/dsm-72/pipseq
Author: dsm-72
Author-email: sumner.magruder@yale.edu
License: Apache Software License 2.0
Keywords: in vitro fertilization pipseq
Classifier: Development Status :: 4 - Beta
Classifier: Intended Audience :: Developers
Classifier: Natural Language :: English
Classifier: Programming Language :: Python :: 3.11
Classifier: License :: OSI Approved :: Apache Software License
Requires-Python: >=3.11
License-File: LICENSE
Requires-Dist: atyp
Requires-Dist: chck
Requires-Dist: nchr
Requires-Dist: nlit
Requires-Dist: psrc
Requires-Dist: xath
Requires-Dist: adic
Requires-Dist: pttn
Requires-Dist: putl
Provides-Extra: dev
Requires-Dist: numpy ; extra == 'dev'
Requires-Dist: pandas ; extra == 'dev'
Requires-Dist: scanpy ; extra == 'dev'
Requires-Dist: scprep ; extra == 'dev'
Requires-Dist: tqdm ; extra == 'dev'
